empathy/__init__.py
empathy/cli.py
empathy-1.1.dist-info/licenses/LICENSE
empathy-1.1.dist-info/METADATA
empathy-1.1.dist-info/WHEEL
empathy-1.1.dist-info/entry_points.txt
empathy-1.1.dist-info/top_level.txt
empathy-1.1.dist-info/RECORD
